CountryCode/__init__.py
CountryCode/asgi.py
CountryCode/settings.py
CountryCode/urls.py
CountryCode/wsgi.py
countrycode_app/__init__.py
countrycode_app/admin.py
countrycode_app/apps.py
countrycode_app/models.py
countrycode_app/tests.py
countrycode_app/views.py
countrycode_app/migrations/0001_initial.py
countrycode_app/migrations/__init__.py
django_countrycodes-0.1.dist-info/METADATA
django_countrycodes-0.1.dist-info/WHEEL
django_countrycodes-0.1.dist-info/top_level.txt
django_countrycodes-0.1.dist-info/RECORD
